nampi/__init__.py
nampi/zadachki.py
nampi-0.0.10.dist-info/METADATA
nampi-0.0.10.dist-info/WHEEL
nampi-0.0.10.dist-info/top_level.txt
nampi-0.0.10.dist-info/RECORD
