Metadata-Version: 2.2
Name: nampi
Version: 0.0.10
Summary: ///
Home-page: https://github.com/Vika-K228
Author: lalala
Author-email: vikki.flove@gmail.com
Requires-Python: >=3.0
Dynamic: author
Dynamic: author-email
Dynamic: description
Dynamic: description-content-type
Dynamic: home-page
Dynamic: requires-python
Dynamic: summary
